kolors/__init__.py
kolors-0.0.4.dist-info/DESCRIPTION.rst
kolors-0.0.4.dist-info/METADATA
kolors-0.0.4.dist-info/RECORD
kolors-0.0.4.dist-info/WHEEL
kolors-0.0.4.dist-info/metadata.json
kolors-0.0.4.dist-info/top_level.txt
kolors-0.0.4.dist-info/zip-safe
