Metadata-Version: 2.0
Name: kolors
Version: 0.0.4
Summary: Simple and lightweight shell color output function.
Home-page: https://github.com/h3/python-kolors
Author: Maxime Haineault
Author-email: haineault@gmail.com
License: MIT
Platform: UNKNOWN
Classifier: Environment :: Console
Classifier: Intended Audience :: Developers
Classifier: License :: OSI Approved :: MIT License
Classifier: Operating System :: OS Independent
Classifier: Programming Language :: Python
